cod_api/__init__.py
cod_api-2.0.1.dist-info/LICENSE
cod_api-2.0.1.dist-info/METADATA
cod_api-2.0.1.dist-info/WHEEL
cod_api-2.0.1.dist-info/top_level.txt
cod_api-2.0.1.dist-info/RECORD
