Metadata-Version: 2.1
Name: cod-api
Version: 2.0.1
Summary: Call Of Duty API.
Home-page: https://codapi.dev/
Author: Todo Lodo
Author-email: me@todolodo.xyz
Maintainer: Engineer15
Maintainer-email: engineergamer15@gmail.com
License: GPL-3.0
Project-URL: Source Code, https://github.com/TodoLodo2089/cod-python-api
Project-URL: Issue Tracker, https://github.com/TodoLodo2089/cod-python-api/issues
Classifier: Intended Audience :: Developers
Classifier: Operating System :: OS Independent
Classifier: Programming Language :: Python
License-File: LICENSE
Requires-Dist: asyncio
Requires-Dist: aiohttp
Requires-Dist: datetime
Requires-Dist: requests
Requires-Dist: uuid
Requires-Dist: urllib3
Requires-Dist: enum34
